bitchbetterhavemymoney/cli.py
bitchbetterhavemymoney-0.0.0.6.dist-info/METADATA
bitchbetterhavemymoney-0.0.0.6.dist-info/RECORD
bitchbetterhavemymoney-0.0.0.6.dist-info/WHEEL
bitchbetterhavemymoney-0.0.0.6.dist-info/entry_points.txt
bitchbetterhavemymoney-0.0.0.6.dist-info/top_level.txt
