Metadata-Version: 2.1
Name: bitchbetterhavemymoney
Version: 0.0.0.6
Summary: A Python CLI tool to check your Monizze maaltijdcheques.
Home-page: https://github.com/lucassel/bitchbetterhavemymoney
Author: Lucas Selfslagh
License: MIT
Platform: UNKNOWN
Classifier: License :: OSI Approved :: MIT License
Classifier: Programming Language :: Python :: 3
Classifier: Programming Language :: Python :: 3.7
Requires-Dist: selenium
Requires-Dist: pyinsults
